quantasf/__init__.py
quantasf/cli.py
quantasf/data/Data_reader.py
quantasf/data/Fund_crawler(Not_stable).py
quantasf/data/Fund_crawler(slow).py
quantasf/data/Fund_crawler(stable).py
quantasf/data/Proxy_start.py
quantasf/data/Stock_saver(ChunkStore).py
quantasf/data/Stock_saver(VersionStore).py
quantasf/data/__init__.py
quantasf/data/allAShare.csv
quantasf/factors/__init__.py
quantasf-0.0.1.dist-info/DESCRIPTION.rst
quantasf-0.0.1.dist-info/METADATA
quantasf-0.0.1.dist-info/RECORD
quantasf-0.0.1.dist-info/WHEEL
quantasf-0.0.1.dist-info/entry_points.txt
quantasf-0.0.1.dist-info/metadata.json
quantasf-0.0.1.dist-info/top_level.txt
