Metadata-Version: 2.0
Name: quantasf
Version: 0.0.1
Summary: A Python package for computing chinese financial factors.
Home-page: https://github.com/Code37/quantasf
Author: Wenchao Zhang
Author-email: 495673131@qq.com
License: MIT license
Keywords: quantasf
Platform: UNKNOWN
Classifier: Development Status :: 2 - Pre-Alpha
Classifier: Intended Audience :: Developers
Classifier: License :: OSI Approved :: MIT License
Classifier: Natural Language :: English
Classifier: Programming Language :: Python :: 3.5
Classifier: Programming Language :: Python :: 3.6
Classifier: Topic :: Scientific/Engineering
Requires-Dist: Click (>=6.0)
